func2argparse/__init__.py
func2argparse/_version.py
func2argparse/logging.ini
func2argparse-0.0.6.dist-info/METADATA
func2argparse-0.0.6.dist-info/WHEEL
func2argparse-0.0.6.dist-info/top_level.txt
func2argparse-0.0.6.dist-info/RECORD
