Metadata-Version: 2.1
Name: func2argparse
Version: 0.0.6
Summary: Convert python functions to argparse objects
Author-email: Acellera <info@acellera.com>
Project-URL: Homepage, https://github.com/Acellera/func2argparse
Project-URL: Bug Tracker, https://github.com/Acellera/func2argparse/issues
Classifier: Programming Language :: Python :: 3
Classifier: Operating System :: POSIX :: Linux
Requires-Python: >=3.9
